<?xml version="1.0" encoding="UTF-8"?>
<!-- Copyright 2012 Arseniy Isakov Licensed under the Apache License, Version 
	2.0 (the "License"); you may not use this file except in compliance with 
	the License. You may obtain a copy of the License at http://www.apache.org/licenses/LICENSE-2.0 
	Unless required by applicable law or agreed to in writing, software distributed 
	under the License is distributed on an "AS IS" BASIS, WITHOUT WARRANTIES 
	OR CONDITIONS OF ANY KIND, either express or implied. See the License for 
	the specific language governing permissions and limitations under the License. -->
<j:jelly trim="false" xmlns:j="jelly:core" xmlns:u="jelly:util"
	xmlns:a="jelly:ant" xmlns="http://www.w3.org/1999/xhtml" xmlns:h="http://java.sun.com/jsf/html"
	xmlns:f="http://java.sun.com/jsf/core" xmlns:ui="http://java.sun.com/jsf/facelets"
	xmlns:p="http://primefaces.org/ui" xmlns:x="jelly:xml">

	<p:dialog header="Lov" widgetVar="lov${lov.uuid.replaceAll('\-','')}"
		resizable="false" >
 		<h:panelGrid columns="2">
			<p:commandButton xmlns:p="http://primefaces.org/ui"
				value="Search"
				actionListener="#{${model.uicontainer}binding.current${lov.optionsSrcLnk.name}.search}"
				update="${lov.propertiesExtender['canvasPath']}:table${lov.uuid.replaceAll('\-','')}"></p:commandButton>
			<p:commandButton xmlns:p="http://primefaces.org/ui"
				value="Query"
				actionListener="#{${model.uicontainer}binding.current${lov.optionsSrcLnk.name}.query}"
				update="${lov.propertiesExtender['canvasPath']}:table${lov.uuid.replaceAll('\-','')}"></p:commandButton>
		</h:panelGrid>

		<p:dataTable var="row" id="table${lov.uuid.replaceAll('\-','')}"
			value="#{${model.uicontainer}binding.current${lov.optionsSrcLnk.name}.lazyModel}"
			paginator="true" rows="5" lazy="true"
			paginatorTemplate="{RowsPerPageDropdown}  {PreviousPageLink}  {NextPageLink}"
			rowsPerPageTemplate="5,10,15" selectionMode="single" rowKey="#{row}">

			<p:ajax event="rowSelect"
				listener="#{${model.uicontainer}binding.current${lov.optionsSrcLnk.name}.setGridCurrentRow}" />

			<j:forEach items="${lov.displayedFields.iterator()}" var="field">
				<p:column headerText="${field.displayLabel}">

				<ui:fragment rendered="#{${model.uicontainer}binding.current${lov.optionsSrcLnk.name}.queryMode}">
			       <h:panelGrid columns="2" style="${field.css}">
	                <j:invokeStatic className="org.apache.commons.lang.StringUtils" method="capitalize" var="capDisplayExpression">
		               <j:arg type="java.lang.String" value="${field.displayExpression}" />
	                </j:invokeStatic>
				    <p:selectOneMenu immediate="true" style="width:40px" value="#{row.comparator${capDisplayExpression}}">
					   <f:selectItem itemLabel="=" itemValue="EQ" />
					   <f:selectItem itemLabel=">" itemValue="GT" />
					   <f:selectItem itemLabel=">=" itemValue="GTEQ" />
					   <f:selectItem itemLabel="&lt;" itemValue="LT" />
					   <f:selectItem itemLabel="&lt;=" itemValue="LTEQ" />
					   <f:selectItem itemLabel="%" itemValue="LIKE" />
	                   <p:ajax update="@this"/>
				    </p:selectOneMenu>
					<p:inputText value="#{row.${field.displayExpression}}" style="width:100%" >
					   <p:ajax event="focus" listener="#{${model.uicontainer}binding.current${lov.optionsSrcLnk.name}.onFocusEvent}"/>
					   <p:ajax event="blur" />
					</p:inputText>

                   </h:panelGrid>
				</ui:fragment>
				<ui:fragment rendered="#{!${model.uicontainer}binding.current${lov.optionsSrcLnk.name}.queryMode}">
					<h:outputText value="#{row.${field.displayExpression}}" style="${field.css};">
					</h:outputText>
				</ui:fragment>
				</p:column>
			</j:forEach>
		</p:dataTable>
    
	<x:element name="p:commandButton" URI="http://primefaces.org/ui">
		<x:attribute name="value">Submit</x:attribute>
		<x:attribute name="oncomplete">lov${lov.uuid.replaceAll('\-','')}.hide();</x:attribute>
		<j:choose>
			<j:when test="${lov.propertiesExtender['OnValueChanged'] != ''}">
				<x:attribute name="update" trim="true">${lov.propertiesExtender['OnValueChanged']}
				</x:attribute>
			</j:when>
		</j:choose>
		<x:attribute name="actionListener">#{${model.uicontainer}binding.current${lov.optionsSrcLnk.name}.returnResult}</x:attribute>
	</x:element>
			

	</p:dialog>


</j:jelly>
